dictionary/__init__.py
dictionary/dictionary.py
cs453_assignment_1_denizhan_kemeroz-2.0.0.dist-info/METADATA
cs453_assignment_1_denizhan_kemeroz-2.0.0.dist-info/WHEEL
cs453_assignment_1_denizhan_kemeroz-2.0.0.dist-info/top_level.txt
cs453_assignment_1_denizhan_kemeroz-2.0.0.dist-info/RECORD
